.gitignore
LICENSE
MANIFEST.in
README.md
VERSION
example_validations.py
requirements.txt
setup.py
test.sh
test.zip
PyFastaValidator/__init__.py
PyFastaValidator/exceptions.py
PyFastaValidator/py_fasta_validator.py
PyFastaValidator/validate.py
PyFastaValidator/version.py
py_fasta_validator.egg-info/PKG-INFO
py_fasta_validator.egg-info/SOURCES.txt
py_fasta_validator.egg-info/dependency_links.txt
py_fasta_validator.egg-info/entry_points.txt
py_fasta_validator.egg-info/top_level.txt
py_fasta_validator.egg-info/zip-safe
src/Makefile
src/fasta_validate.c
src/fasta_validate.h
test/code.fasta
test/code.fasta.gz
test/code.fasta.old
test/code.fasta.old.gz
test/duplicates_no_spaces.fasta
test/duplicates_no_spaces.fasta.gz
test/duplicates_with_spaces.fasta
test/duplicates_with_spaces.fasta.gz
test/good.fasta
test/good.fasta.gz
test/good_mixed.fasta
test/good_mixed.fasta.gz
test/good_multiline.fasta
test/good_multiline.fasta.gz
test/no_first_line.fasta
test/no_first_line.fasta.gz
test/space.fasta
test/space.fasta.gz