Metadata-Version: 2.1
Name: py-fasta-validator
Version: 0.6
Summary: A small, lightweight, fast fasta validator written in C
Home-page: https://github.com/linsalrob/py_fasta_validator
Author: Rob Edwards
Author-email: raedwards@gmail.com
License: The MIT License (MIT)
Keywords: bioinformatics genome genomics fasta
Platform: any
Classifier: Development Status :: 4 - Beta
Classifier: Intended Audience :: Science/Research
Classifier: License :: OSI Approved :: MIT License
Classifier: Natural Language :: English
Classifier: Operating System :: MacOS :: MacOS X
Classifier: Operating System :: POSIX :: Linux
Classifier: Operating System :: Unix
Classifier: Programming Language :: Python :: 3.0
Classifier: Topic :: Scientific/Engineering :: Bio-Informatics
License-File: LICENSE
